py_subconverter/__init__.py
py_subconverter/__main__.py
py_subconverter/clash_generator.py
py_subconverter/cli.py
py_subconverter/dler_api_client.py
py_subconverter/ini_parser.py
py_subconverter/models.py
py_subconverter/proxy_parser.py
py_subconverter/sub_converter.py
py_subconverter/subscription_converter.py
subconverter_py-0.1.2.dist-info/licenses/LICENSE
subconverter_py-0.1.2.dist-info/METADATA
subconverter_py-0.1.2.dist-info/WHEEL
subconverter_py-0.1.2.dist-info/entry_points.txt
subconverter_py-0.1.2.dist-info/top_level.txt
subconverter_py-0.1.2.dist-info/RECORD
