Metadata-Version: 2.4
Name: subconverter-py
Version: 0.1.2
Summary: Python-based proxy subscription converter for Clash
Author-email: Gency Lee <gency@example.com>
License: MIT
Project-URL: Homepage, https://github.com/gencylee/subconverter-py
Project-URL: Documentation, https://github.com/gencylee/subconverter-py#readme
Project-URL: Repository, https://github.com/gencylee/subconverter-py
Project-URL: Bug Tracker, https://github.com/gencylee/subconverter-py/issues
Keywords: clash,proxy,subscription,converter,subconverter
Classifier: Development Status :: 4 - Beta
Classifier: Intended Audience :: Developers
Classifier: Intended Audience :: End Users/Desktop
Classifier: License :: OSI Approved :: MIT License
Classifier: Programming Language :: Python :: 3
Classifier: Programming Language :: Python :: 3.9
Classifier: Programming Language :: Python :: 3.10
Classifier: Programming Language :: Python :: 3.11
Classifier: Programming Language :: Python :: 3.12
Classifier: Topic :: Internet :: Proxy Servers
Classifier: Topic :: Utilities
Requires-Python: >=3.9
License-File: LICENSE
Requires-Dist: pydantic>=2.0.0
Requires-Dist: PyYAML>=6.0
Requires-Dist: requests>=2.28.0
Requires-Dist: python-dotenv>=0.20.0
Provides-Extra: dev
Requires-Dist: pytest>=7.0.0; extra == "dev"
Requires-Dist: pytest-cov>=4.0.0; extra == "dev"
Requires-Dist: black>=23.0.0; extra == "dev"
Requires-Dist: flake8>=6.0.0; extra == "dev"
Requires-Dist: mypy>=1.0.0; extra == "dev"
Dynamic: license-file
